td_ml_map_segment_profiles/__init__.py
td_ml_map_segment_profiles/map_segments_to_profiles.py
td_ml_map_segment_profiles-0.0.3.dist-info/METADATA
td_ml_map_segment_profiles-0.0.3.dist-info/WHEEL
td_ml_map_segment_profiles-0.0.3.dist-info/licenses/LICENSE
td_ml_map_segment_profiles-0.0.3.dist-info/RECORD
