Metadata-Version: 2.1
Name: td_ml_map_segment_profiles
Version: 0.0.3
Summary: Extract Parent Segment Stats
Project-URL: Homepage, https://github.com/treasure-data-ps/td_ml_libraries/tree/main/td_ml_map_segment_profiles
Project-URL: Bug Tracker, https://github.com/treasure-data-ps/td_ml_libraries/tree/main/td_ml_map_segment_profiles
Author-email: Dilyan Kovachev <pruchka@gmail.com>
License: Copyright © 2022 Treasure Data, Inc. (or its affiliates). All rights reserved
License-File: LICENSE
Classifier: Operating System :: OS Independent
Classifier: Programming Language :: Python :: 3
Requires-Python: >=3.8
